{
  "data": "08-09-2025",
  "secaoDefault": "DO1",
  "defaults": {
    "scrape_detail": false,
    "fallback_date_if_missing": false,
    "max_links": 3,
    "max_scrolls": 8,
    "scroll_pause_ms": 150,
    "stable_rounds": 1,
    "label1": "(Órgão|Orgao)",
    "label2": "(Secretaria|Unidade|Subordinad)",
    "label3": null,
    "debug_dump": false,
    "summary_lines": null,
    "summary_mode": "center"
  },
  "combos": [
    {
      "key1_type": "text",
      "key1": "Ministério da Defesa",
      "key2_type": "text",
      "key2": "Agência Nacional de Aviação Civil",
      "key3_type": null,
      "key3": null,
      "label1": "",
      "label2": "",
      "label3": ""
    },
    {
      "key1_type": "text",
      "key1": "Ministério da Defesa",
      "key2_type": "text",
      "key2": "Agência Nacional de Energia Elétrica",
      "key3_type": null,
      "key3": null,
      "label1": "",
      "label2": "",
      "label3": ""
    },
    {
      "key1_type": "text",
      "key1": "Ministério da Defesa",
      "key2_type": "text",
      "key2": "Agência Nacional de Mineração",
      "key3_type": null,
      "key3": null,
      "label1": "",
      "label2": "",
      "label3": ""
    },
    {
      "key1_type": "text",
      "key1": "Ministério da Defesa",
      "key2_type": "text",
      "key2": "Agência Nacional de Saúde Suplementar",
      "key3_type": null,
      "key3": null,
      "label1": "",
      "label2": "",
      "label3": ""
    },
    {
      "key1_type": "text",
      "key1": "Ministério da Defesa",
      "key2_type": "text",
      "key2": "Agência Nacional de Telecomunicações",
      "key3_type": null,
      "key3": null,
      "label1": "",
      "label2": "",
      "label3": ""
    },
    {
      "key1_type": "text",
      "key1": "Ministério da Defesa",
      "key2_type": "text",
      "key2": "Agência Nacional de Transportes Aquaviários",
      "key3_type": null,
      "key3": null,
      "label1": "",
      "label2": "",
      "label3": ""
    },
    {
      "key1_type": "text",
      "key1": "Ministério da Defesa",
      "key2_type": "text",
      "key2": "Agência Nacional de Transportes Terrestres",
      "key3_type": null,
      "key3": null,
      "label1": "",
      "label2": "",
      "label3": ""
    },
    {
      "key1_type": "text",
      "key1": "Ministério da Defesa",
      "key2_type": "text",
      "key2": "Agência Nacional de Vigilância Sanitária",
      "key3_type": null,
      "key3": null,
      "label1": "",
      "label2": "",
      "label3": ""
    },
    {
      "key1_type": "text",
      "key1": "Ministério da Defesa",
      "key2_type": "text",
      "key2": "Agência Nacional de Águas e Saneamento Básico",
      "key3_type": null,
      "key3": null,
      "label1": "",
      "label2": "",
      "label3": ""
    },
    {
      "key1_type": "text",
      "key1": "Ministério da Defesa",
      "key2_type": "text",
      "key2": "Agência Nacional do Cinema",
      "key3_type": null,
      "key3": null,
      "label1": "",
      "label2": "",
      "label3": ""
    },
    {
      "key1_type": "text",
      "key1": "Ministério da Defesa",
      "key2_type": "text",
      "key2": "Agência Nacional do Petróleo, Gás Natural e Biocombustíveis",
      "key3_type": null,
      "key3": null,
      "label1": "",
      "label2": "",
      "label3": ""
    },
    {
      "key1_type": "text",
      "key1": "Ministério da Defesa",
      "key2_type": "text",
      "key2": "Comando da Aeronáutica",
      "key3_type": null,
      "key3": null,
      "label1": "",
      "label2": "",
      "label3": ""
    },
    {
      "key1_type": "text",
      "key1": "Ministério da Defesa",
      "key2_type": "text",
      "key2": "Comando da Marinha",
      "key3_type": null,
      "key3": null,
      "label1": "",
      "label2": "",
      "label3": ""
    },
    {
      "key1_type": "text",
      "key1": "Ministério da Defesa",
      "key2_type": "text",
      "key2": "Comissão Nacional de Energia Nuclear",
      "key3_type": null,
      "key3": null,
      "label1": "",
      "label2": "",
      "label3": ""
    },
    {
      "key1_type": "text",
      "key1": "Ministério da Defesa",
      "key2_type": "text",
      "key2": "Comissão de Valores Mobiliários",
      "key3_type": null,
      "key3": null,
      "label1": "",
      "label2": "",
      "label3": ""
    },
    {
      "key1_type": "text",
      "key1": "Ministério da Defesa",
      "key2_type": "text",
      "key2": "Comissão de Ética Pública",
      "key3_type": null,
      "key3": null,
      "label1": "",
      "label2": "",
      "label3": ""
    },
    {
      "key1_type": "text",
      "key1": "Ministério da Defesa",
      "key2_type": "text",
      "key2": "Conselho Administrativo de Defesa Econômica",
      "key3_type": null,
      "key3": null,
      "label1": "",
      "label2": "",
      "label3": ""
    },
    {
      "key1_type": "text",
      "key1": "Ministério da Defesa",
      "key2_type": "text",
      "key2": "Conselho Administrativo de Recursos Fiscais",
      "key3_type": null,
      "key3": null,
      "label1": "",
      "label2": "",
      "label3": ""
    },
    {
      "key1_type": "text",
      "key1": "Ministério de Portos e Aeroportos",
      "key2_type": "text",
      "key2": "Agência Nacional de Aviação Civil",
      "key3_type": null,
      "key3": null,
      "label1": "",
      "label2": "",
      "label3": ""
    },
    {
      "key1_type": "text",
      "key1": "Ministério de Portos e Aeroportos",
      "key2_type": "text",
      "key2": "Agência Nacional de Energia Elétrica",
      "key3_type": null,
      "key3": null,
      "label1": "",
      "label2": "",
      "label3": ""
    }
  ],
  "output": {
    "pattern": "{secao}_{date}_{idx}.json",
    "report": "batch_report.json"
  }
}